{
    "dersler": [
        {
            "dersAdi": "Ders 1",
            "dersIcerik": "Lorem ipsum, dolor sit amet consectetur adipisicing elit. Perferendis iste ab aliquid quaerat possimusexpedita illum iure ullam inventore hic magnam, accusamus, accusantium amet sapiente consequuntur qui totam,molestias maxime numquam veritatis ipsa quos. Culpa reprehenderit cum cumque necessitatibus voluptatumlaborum repellat? Quas est velit ipsa voluptate illo laboriosam reiciendis cum laudantium itaque sint dictaquod sapiente fugiat tempora id nobis omnis nisi, adipisci eius saepe optio, rerum esse? Impedit esse exneque repellat vero recusandae obcaecati at ducimus corporis a tenetur quas quaerat vitae, evenietaspernatur minus optio, amet repudiandae tempore veniam, animi magnam! Dolorum praesentium odit, molestiasducimus consectetur non, ut quae odio voluptate placeat quasi sequi ea earum beatae totam corporis dictaitaque nisi accusantium ullam natus. Quibusdam architecto quos, in iure deleniti dolores error ea ipsum quoillo, maiores eaque debitis cum pariatur, nihil minima eius tempora. Dolor vitae autem non. Doloremquefacilis ea assumenda id? Commodi, dolorum reiciendis! Voluptas asperiores harum nesciunt ad itaque deseruntrepellat omnis reprehenderit aut quisquam quaerat, laudantium minima, quam provident architecto voluptate etplaceat in veritatis fugiat commodi unde ut! Neque, ut? Corrupti recusandae ad earum magni placeat numquam?Cumque delectus beatae quod vel! Accusantium dignissimos doloribus sequi incidunt nisi praesentium istevoluptates exercitationem, numquam sit facere, excepturi eveniet veniam, temporibus esse? Inventore illosequi blanditiis culpa quia iure eveniet quis odio. Et laborum quaerat nihil in eveniet? Delectus nullatenetur aliquam debitis enim qui, pariatur quia ea ipsa, illo dolore cum quibusdam optio sequi nam quo isteet itaque. Facere tempore, placeat sit error voluptas at eum incidunt excepturi fuga voluptates dolorumminus porro sapiente quasi deserunt consequuntur culpa? Ex in sequi asperiores, suscipit ullam dolore quis,at adipisci accusamus minima voluptas corrupti fuga quidem totam obcaecati? Eveniet placeat hic quia oditfugit iure numquam temporibus facilis dolorem ipsa expedita molestiae velit, magni modi ex eius explicaboquas, soluta aliquam eligendi a tenetur ipsam ratione. Similique impedit, omnis doloribus natus quam laborequae maxime totam architecto facere molestias accusantium eveniet dolorum dolor. Dolore esse maiores illodoloribus obcaecati quis ut! Quisquam, a nihil asperiores harum perspiciatis pariatur. Maiores, minima! Illoomnis consequuntur error dicta consectetur voluptatibus quibusdam? Rem tempore officiis nulla iusto doloredoloremque omnis repellat in consequuntur? Facere molestias sit fugiat porro soluta? Commodi delectus eum,voluptatibus suscipit expedita illo rerum. In ratione doloremque vero, eos tenetur quia corrupti doloremmagnam nisi commodi voluptatem aspernatur, architecto fuga, nostrum cumque ipsa laborum suscipit assumendablanditiis inventore ut! Sequi nisi officiis temporibus quidem, architecto doloremque laboriosam magnamsaepe eaque. Quisquam accusantium sunt rem distinctio repellendus quasi iure quo fugit aliquid hic ut porrosequi eaque tenetur rerum, labore, obcaecati dolor, excepturi possimus aspernatur! Consectetur temporaprovident laboriosam eos quasi minima voluptate reprehenderit dolore totam, incidunt aut maxime ut sit, odiovoluptatem! Ipsa eos reiciendis maxime hic ex, quod sit enim sed id, omnis minus illum nesciunt aperiamminima sunt numquam. Delectus, corporis quisquam fugiat ipsa saepe ratione voluptas et laboriosam dictaaspernatur similique voluptatem earum qui. Ea exercitationem a dolorem!"
        },
        {
            "dersAdi": "Ders 2",
            "dersIcerik": "Ders 2 İçeriği..."
        },
        {
            "dersAdi": "Ders 3",
            "dersIcerik": "Ders 3 İçeriği..."
        },
        {
            "dersAdi": "Ders 4",
            "dersIcerik": "Ders 4 İçeriği..."
        },
        {
            "dersAdi": "Ders 5",
            "dersIcerik": "Ders 5 İçeriği..."
        },
        {
            "dersAdi": "Ders 6",
            "dersIcerik": "Ders 6 İçeriği..."
        },
        {
            "dersAdi": "Ders 7",
            "dersIcerik": "Ders 7 İçeriği..."
        },
        {
            "dersAdi": "Ders 8",
            "dersIcerik": "Ders 8 İçeriği..."
        }
    ]
}